zhouyuqinsdkdemo/__init__.py
zhouyuqin_python_sdk_demo-0.1.0.dist-info/METADATA
zhouyuqin_python_sdk_demo-0.1.0.dist-info/WHEEL
zhouyuqin_python_sdk_demo-0.1.0.dist-info/top_level.txt
zhouyuqin_python_sdk_demo-0.1.0.dist-info/RECORD
