Metadata-Version: 2.1
Name: zhouyuqin-python-sdk-demo
Version: 0.1.0
Summary: The demo of zhouyuqin Python SDK.
Home-page: 
Author: zhouyuqin
Author-email: 
License: Apache License 2.0
Platform: any
Requires-Dist: zhouyuqin-sdk-core (==0.1.0)
